fairdiverse/__init__.py
fairdiverse/main.py
fairdiverse/test.py
fairdiverse/recommendation/__init__.py
fairdiverse/recommendation/evaluator.py
fairdiverse/recommendation/llm_rec.py
fairdiverse/recommendation/metric.py
fairdiverse/recommendation/process_dataset.py
fairdiverse/recommendation/reranker.py
fairdiverse/recommendation/sampler.py
fairdiverse/recommendation/trainer.py
fairdiverse/recommendation/base_model/__init__.py
fairdiverse/recommendation/base_model/abstract_model.py
fairdiverse/recommendation/base_model/bpr.py
fairdiverse/recommendation/base_model/bpr_seq.py
fairdiverse/recommendation/base_model/gru4rec.py
fairdiverse/recommendation/base_model/layers.py
fairdiverse/recommendation/base_model/mf.py
fairdiverse/recommendation/base_model/sasrec.py
fairdiverse/recommendation/llm/__init__.py
fairdiverse/recommendation/llm/grounder.py
fairdiverse/recommendation/llm/llm_caller.py
fairdiverse/recommendation/llm/prompt_constructer.py
fairdiverse/recommendation/rank_model/APR.py
fairdiverse/recommendation/rank_model/Abstract_Ranker.py
fairdiverse/recommendation/rank_model/DPR.py
fairdiverse/recommendation/rank_model/FOCF.py
fairdiverse/recommendation/rank_model/FairDual.py
fairdiverse/recommendation/rank_model/FairNeg.py
fairdiverse/recommendation/rank_model/IPS.py
fairdiverse/recommendation/rank_model/Minmax_SGD.py
fairdiverse/recommendation/rank_model/Reg.py
fairdiverse/recommendation/rank_model/SDRO.py
fairdiverse/recommendation/rank_model/__init__.py
fairdiverse/recommendation/rerank_model/Abstract_Reranker.py
fairdiverse/recommendation/rerank_model/CPFair.py
fairdiverse/recommendation/rerank_model/FairRec.py
fairdiverse/recommendation/rerank_model/FairRecPlus.py
fairdiverse/recommendation/rerank_model/FairSync.py
fairdiverse/recommendation/rerank_model/PMMF.py
fairdiverse/recommendation/rerank_model/RAIF.py
fairdiverse/recommendation/rerank_model/TaxRank.py
fairdiverse/recommendation/rerank_model/Welf.py
fairdiverse/recommendation/rerank_model/__init__.py
fairdiverse-1.0.0.dist-info/LICENSE
fairdiverse-1.0.0.dist-info/METADATA
fairdiverse-1.0.0.dist-info/WHEEL
fairdiverse-1.0.0.dist-info/top_level.txt
fairdiverse-1.0.0.dist-info/RECORD
