Metadata-Version: 2.1
Name: fairdiverse
Version: 1.0.0
Summary: A unified, comprehensive fairness- and diversity-aware IR library
Home-page: https://github.com/XuChen0427/FairDiverse
Author: Chen Xu
Author-email: chenxu0427ruc@gmail.com
Classifier: License :: OSI Approved :: MIT License
Requires-Python: >=3.6
License-File: LICENSE
Requires-Dist: numpy (>=1.20.3)
Requires-Dist: torch (>=1.11.0)
Requires-Dist: PyYAML (>=6.0)
Requires-Dist: pandas (>=1.2.0)
Requires-Dist: scipy
Requires-Dist: cvxpy
Requires-Dist: tqdm (>=4.65.0)
Requires-Dist: scikit-learn
Requires-Dist: pot
Requires-Dist: mip (>=1.15.0)
Requires-Dist: gurobipy (>=12.0.1)
